AUTHORS.rst
CONTRIBUTING.rst
HISTORY.rst
LICENSE
MANIFEST.in
README.rst
requirements.txt
setup.cfg
setup.py
src/jukeboxmaya/__init__.py
src/jukeboxmaya/commands.py
src/jukeboxmaya/common.py
src/jukeboxmaya/constants.py
src/jukeboxmaya/launcher.py
src/jukeboxmaya/main.py
src/jukeboxmaya/mayapylauncher.py
src/jukeboxmaya/menu.py
src/jukeboxmaya/plugins.py
src/jukeboxmaya.egg-info/PKG-INFO
src/jukeboxmaya.egg-info/SOURCES.txt
src/jukeboxmaya.egg-info/dependency_links.txt
src/jukeboxmaya.egg-info/entry_points.txt
src/jukeboxmaya.egg-info/not-zip-safe
src/jukeboxmaya.egg-info/requires.txt
src/jukeboxmaya.egg-info/top_level.txt
src/jukeboxmaya/addons/__init__.py
src/jukeboxmaya/addons/mayaconfiger/__init__.py
src/jukeboxmaya/addons/mayaconfiger/mayaconfiger.py
src/jukeboxmaya/addons/mayagenesis/__init__.py
src/jukeboxmaya/addons/mayagenesis/mayagenesis.ini
src/jukeboxmaya/addons/mayagenesis/mayagenesis.py
src/jukeboxmaya/addons/mayamgmt/__init__.py
src/jukeboxmaya/addons/mayamgmt/mayamgmt.py
src/jukeboxmaya/addons/mayawidgettooltip/mayawidgettooltip.py
src/jukeboxmaya/addons/reftracker/reftracker.py
src/jukeboxmaya/addons/scenerelease/scenerelease.py
src/jukeboxmaya/gui/__init__.py
src/jukeboxmaya/gui/main.py
src/jukeboxmaya/mayaplugins/__init__.py
src/jukeboxmaya/mayaplugins/jbasset.py
src/jukeboxmaya/mayaplugins/jbreftrack.py
src/jukeboxmaya/mayaplugins/jbscene.py
src/jukeboxmaya/reftrack/__init__.py
src/jukeboxmaya/reftrack/asset.py
src/jukeboxmaya/reftrack/refobjinter.py
test/test_common.py
test/test_mayaplugins.py
test/test_menu.py
test/test_sphinx.py