Metadata-Version: 1.1
Name: jukeboxmaya
Version: 3.2.0
Summary: Jukebox Pipeline for Maya
Home-page: https://github.com/JukeboxPipeline/jukeboxmaya
Author: David Zuber
Author-email: zuber.david@gmx.de
License: BSD
Keywords: jukeboxmaya
Platform: UNKNOWN
Classifier: Development Status :: 2 - Pre-Alpha
Classifier: Intended Audience :: Developers
Classifier: License :: OSI Approved :: BSD License
Classifier: Natural Language :: English
Classifier: Programming Language :: Python :: 2.7
